README.rst
setup.cfg
setup.py
github_file/__init__.py
github_file/cli.py
github_file.egg-info/PKG-INFO
github_file.egg-info/SOURCES.txt
github_file.egg-info/dependency_links.txt
github_file.egg-info/entry_points.txt
github_file.egg-info/not-zip-safe
github_file.egg-info/requires.txt
github_file.egg-info/top_level.txt